kliko/__init__.py
kliko/cli.py
kliko/django.py
kliko/django_form.py
kliko/docker.py
kliko/exceptions.py
kliko/testutil.py
kliko/validate.py
kliko/version.py
kliko/schemas/2.yml
kliko-0.6.1.data/scripts/kliko-run
kliko-0.6.1.data/scripts/kliko-validate
kliko-0.6.1.data/scripts/kliko-validate.py
kliko-0.6.1.dist-info/DESCRIPTION.rst
kliko-0.6.1.dist-info/METADATA
kliko-0.6.1.dist-info/RECORD
kliko-0.6.1.dist-info/WHEEL
kliko-0.6.1.dist-info/metadata.json
kliko-0.6.1.dist-info/pbr.json
kliko-0.6.1.dist-info/top_level.txt
test/__init__.py
test/requirements.txt
test/test_cli.py
test/test_django_form.py
test/test_docker.py
test/test_settings.py
test/test_validate.py
