Metadata-Version: 2.0
Name: kliko
Version: 0.6.1
Summary: Scientific Compute Container Spec Parser
Home-page: https://github.com/gijzelaerr/kliko
Author: Gijs Molenaar
Author-email: gijs@pythonic.nl
License: GPL2
Keywords: science docker yaml json
Platform: UNKNOWN
Classifier: Development Status :: 3 - Alpha
Classifier: Intended Audience :: Science/Research
Classifier: License :: OSI Approved :: GNU General Public License v2 (GPLv2)
Classifier: Operating System :: POSIX
Classifier: Programming Language :: Python :: 2.7
Classifier: Programming Language :: Python :: 3.4
Classifier: Programming Language :: Python :: 3.5
Classifier: Programming Language :: Python :: Implementation :: PyPy
Classifier: Topic :: Scientific/Engineering
Classifier: Topic :: Software Development :: Build Tools
Classifier: Topic :: System :: Distributed Computing
Classifier: Topic :: System :: Emulators
Classifier: Topic :: System :: Operating System Kernels :: Linux
Requires-Dist: PyYAML
Requires-Dist: docopt
Requires-Dist: future
Requires-Dist: pykwalify
Provides-Extra: django
Requires-Dist: django; extra == 'django'
Requires-Dist: django-form-utils; extra == 'django'
Provides-Extra: docker
Requires-Dist: docker-py; extra == 'docker'
